{
  "numu_cc": {
    "trck": "lambda E: 6.45222629e-01/(np.exp((1.27056003e+00 - np.log10(E))/1.70585447e-01) + 1.) + 1.18734945e-01",
    "cscd": "lambda E: 1. - (6.45222629e-01/(np.exp((1.27056003e+00 - np.log10(E))/1.70585447e-01) + 1.) + 1.18734945e-01)"
  },
  "nuall_nc": {
    "trck": "lambda E: -8.73088402e-02*np.exp(-E/4.38894060e+01) + 1.72538102e-01",
    "cscd": "lambda E: 1. - (-8.73088402e-02*np.exp(-E/4.38894060e+01) + 1.72538102e-01)"
  },
  "nue_cc": {
    "trck": "lambda E: -1.66238490e+02*np.exp(-E/1.05090776e+05) + 1.66345242e+02",
    "cscd": "lambda E: 1. - (-1.66238490e+02*np.exp(-E/1.05090776e+05) + 1.66345242e+02)"
  },
  "nutau_cc": {
    "trck": "lambda E: -1.99361163e-01*np.exp(-E/4.31638189e+01) + 2.76546697e-01",
    "cscd": "lambda E: 1. - (-1.99361163e-01*np.exp(-E/4.31638189e+01) + 2.76546697e-01)"
  }
}
